{
  "id": 62,
  "title_jp": "ファイナルファンタジーXIV",
  "title_en": "Final Fantasy XIV",
  "developer": "スクエニ",
  "publisher": "スクエニ",
  "year": 2010,
  "platform": [
    "Multi"
  ],
  "genre": "MMORPG",
  "sales_world": "3000万+ ID",
  "primary": "EXP",
  "secondary": [
    "NAR"
  ],
  "social_axis": "協力",
  "slug": "final-fantasy-xiv",
  "file": "data/games/062-final-fantasy-xiv.json",
  "concept": "「物語のためにMMOがある」という再生成された設計、長文シナリオが拡張ごとに高評価を獲得し続けるMMORPG。",
  "target": "20-40代、MMORPGファン + 物語消費を求める層、特に「漆黒のヴィランズ」以降の新規参入者。"
}
