{
  "id": 212,
  "title_jp": "マナー・ローズ",
  "title_en": "Manor Lords",
  "developer": "Slavic Magic (Greg Styczeń)",
  "publisher": "Hooded Horse",
  "year": 2024,
  "platform": [
    "PC",
    "Xbox"
  ],
  "genre": "中世都市建設／RTS",
  "sales_jp": "",
  "sales_world": "300万本+ (2025年2月)",
  "primary": "EXP",
  "secondary": [
    "NAR"
  ],
  "social_axis": "ソロ",
  "popularity": "ソロ開発者による14世紀フランケン地方を題材にした硬派な中世都市建設。発売前 Steam ウィッシュリスト300万超、発売週末の同時接続17万超で都市建設ジャンルの記録を塗り替え、Early Access開始3週間で200万本到達。",
  "slug": "manor-lords",
  "file": "data/games/212-manor-lords.json",
  "concept": "封建領主となり、史実考証に基づく14世紀の村を一軒ずつ手作りで育て、領地を拡大しながら時にはRTS戦闘で防衛する「歴史リアリズム×都市建設」のハイブリッド。",
  "target": "Banished/Anno/Total War 系の硬派ストラテジーファン。地形に沿った中世村落の有機的な発展や、税・食糧・農業3圃制といった経済シミュレーションをじっくり味わいたい単独プレイ志向のプレイヤー。",
  "tags": [
    "indie"
  ]
}
